renson_endura_delta/__init__.py
renson_endura_delta/field_enum.py
renson_endura_delta/general_enum.py
renson_endura_delta/renson.py
renson_endura_delta-1.7.2.dist-info/METADATA
renson_endura_delta-1.7.2.dist-info/WHEEL
renson_endura_delta-1.7.2.dist-info/top_level.txt
renson_endura_delta-1.7.2.dist-info/RECORD
