Metadata-Version: 2.1
Name: renson-endura-delta
Version: 1.7.2
Summary: Unofficial Renson endura delta Python library
Home-page: https://github.com/jimmyd-be/Renson-endura-delta-library
Author: JimmyD-be
License: MIT
Project-URL: Bug Tracker, https://github.com/jimmyd-be/Renson-endura-delta-library/issues
Platform: UNKNOWN
Requires-Python: >=3.6
